aiohttp_metrics/__init__.py
aiohttp_metrics/metrics.py
aiohttp_metrics-0.1.1.dist-info/LICENSE
aiohttp_metrics-0.1.1.dist-info/WHEEL
aiohttp_metrics-0.1.1.dist-info/METADATA
aiohttp_metrics-0.1.1.dist-info/RECORD
